[
  {
    "image_url": "https://i.ytimg.com/vi/yLIBWf3WPGY/hqdefault.jpg",
    "title": "Community Meeting (January 24, 2023)",
    "description": "https://github.com/asyncapi/community/issues/569.",
    "videoId": "yLIBWf3WPGY"
  },
  {
    "image_url": "https://i.ytimg.com/vi/6hltg01w004/hqdefault.jpg",
    "title": "Spec 3.0 meeting (January 18, 2023)",
    "description": "https://github.com/asyncapi/community/issues/564.",
    "videoId": "6hltg01w004"
  },
  {
    "image_url": "https://i.ytimg.com/vi/aLDkeuTQU8o/hqdefault.jpg",
    "title": "Design Meeting, 16:00 UTC Tuesday January 16, 2023",
    "description": "https://github.com/asyncapi/community/issues/563.",
    "videoId": "aLDkeuTQU8o"
  },
  {
    "image_url": "https://i.ytimg.com/vi/DnJv6Qm1pl8/hqdefault.jpg",
    "title": "Community Meeting, 08:00 UTC Tuesday January 10, 2023",
    "description": "https://github.com/asyncapi/community/issues/562.",
    "videoId": "DnJv6Qm1pl8"
  },
  {
    "image_url": "https://i.ytimg.com/vi/Va1iQLjEM4s/hqdefault.jpg",
    "title": "Community Meeting (December 13, 2022)",
    "description": "https://github.com/asyncapi/community/issues/549.",
    "videoId": "Va1iQLjEM4s"
  }
]