[
  {
    "image_url": "https://i.ytimg.com/vi/KnXXiv0HEMA/hqdefault.jpg",
    "title": "Governance Board Meeting, Monday November 3rd 2025",
    "description": "https://github.com/asyncapi/community/issues/2116.",
    "videoId": "KnXXiv0HEMA"
  },
  {
    "image_url": "https://i.ytimg.com/vi/KbT7Pw6j46E/hqdefault.jpg",
    "title": "AsyncAPI Online Conference 2025",
    "description": "Join us this year for another edition of the AsyncAPI Online Conference 2025, featuring incredible speakers from around the world ...",
    "videoId": "KbT7Pw6j46E"
  },
  {
    "image_url": "https://i.ytimg.com/vi/gn6765Le_zQ/hqdefault.jpg",
    "title": "AsyncAPI Community WG Meeting, Tuesday September 23rd 2025",
    "description": "https://github.com/asyncapi/community/issues/2066.",
    "videoId": "gn6765Le_zQ"
  },
  {
    "image_url": "https://i.ytimg.com/vi/m-aLlapR2Mg/hqdefault.jpg",
    "title": "AsyncAPI Community WG Meeting , Tuesday September 9th 2025",
    "description": "https://github.com/asyncapi/community/issues/2060.",
    "videoId": "m-aLlapR2Mg"
  },
  {
    "image_url": "https://i.ytimg.com/vi/7vvdmDVZPX0/hqdefault.jpg",
    "title": "AsyncAPI Community WG Meeting , Tuesday July 29th 2025",
    "description": "https://github.com/asyncapi/community/issues/1988.",
    "videoId": "7vvdmDVZPX0"
  }
]