[
  {
    "image_url": "https://i.ytimg.com/vi/Hy3-C6V2ir8/hqdefault.jpg",
    "title": "AsyncAPI Conference Dry Run",
    "description": "Setup and conference prep.",
    "videoId": "Hy3-C6V2ir8"
  },
  {
    "image_url": "https://i.ytimg.com/vi/2WUchTKDPfs/hqdefault.jpg",
    "title": "Marketing WG Meeting, 14:00 UTC Tuesday October 22nd 2024",
    "description": "https://github.com/asyncapi/community/issues/1553.",
    "videoId": "2WUchTKDPfs"
  },
  {
    "image_url": "https://i.ytimg.com/vi/FzRxTpOeIDA/hqdefault.jpg",
    "title": "Design Meeting, 12:00 UTC Thursday October 17th 2024",
    "description": "https://github.com/asyncapi/community/issues/1558.",
    "videoId": "FzRxTpOeIDA"
  },
  {
    "image_url": "https://i.ytimg.com/vi/maMQC97q_6E/hqdefault.jpg",
    "title": "Community Meeting, 8:00 UTC Tuesday October 15th 2024",
    "description": "https://github.com/asyncapi/community/issues/1545.",
    "videoId": "maMQC97q_6E"
  },
  {
    "image_url": "https://i.ytimg.com/vi/P1ZqaVBb6XM/hqdefault.jpg",
    "title": "AsyncAPI Mentorship Program FAQ, 11:00 UTC Thursday October 10th 2024",
    "description": "https://github.com/asyncapi/community/issues/1550.",
    "videoId": "P1ZqaVBb6XM"
  }
]